pdfcombine/__init__.py
pdfcombine/_version.py
pdfcombine/cli/__init__.py
pdfcombine/cli/pdfcombine.py
pdfcombine-1.1.5.dist-info/LICENSE
pdfcombine-1.1.5.dist-info/METADATA
pdfcombine-1.1.5.dist-info/WHEEL
pdfcombine-1.1.5.dist-info/entry_points.txt
pdfcombine-1.1.5.dist-info/top_level.txt
pdfcombine-1.1.5.dist-info/RECORD
