Metadata-Version: 2.1
Name: pdfcombine
Version: 1.1.5
Summary: TeX file formatting
Author-email: Tom de Geus <tom@geus.me>
Project-URL: Source, https://github.com/tdegeus/pdfcombine
Classifier: License :: OSI Approved :: MIT License
Requires-Python: >=3.6
License-File: LICENSE
Requires-Dist: numpy
Requires-Dist: click >=4.0
Requires-Dist: pyyaml >=1.0
Requires-Dist: docopt >=0.6.2
